planner_save.py
satisfactory_planner_save-0.1.3.dist-info/LICENSE
satisfactory_planner_save-0.1.3.dist-info/METADATA
satisfactory_planner_save-0.1.3.dist-info/WHEEL
satisfactory_planner_save-0.1.3.dist-info/entry_points.txt
satisfactory_planner_save-0.1.3.dist-info/top_level.txt
satisfactory_planner_save-0.1.3.dist-info/RECORD
