Metadata-Version: 2.2
Name: satisfactory-planner-save
Version: 0.1.3
Summary: CLI tool for managing Satisfactory Planner saves
Author-email: Jay Woose <jwoose@gmail.com>
Project-URL: repository, https://github.com/jWolo/satisfactory-planner-save.git
License-File: LICENSE
Requires-Dist: selenium>=4.0.0
